LICENSE
MANIFEST.in
README.rst
setup.cfg
setup.py
django_thesaurus.egg-info/PKG-INFO
django_thesaurus.egg-info/SOURCES.txt
django_thesaurus.egg-info/dependency_links.txt
django_thesaurus.egg-info/requires.txt
django_thesaurus.egg-info/top_level.txt
tests/__init__.py
tests/conftest.py
tests/test_import.py
tests/urls.py
thesaurus/__init__.py
thesaurus/admin.py
thesaurus/apps.py
thesaurus/models.py
thesaurus/management/__init__.py
thesaurus/management/commands/__init__.py
thesaurus/management/commands/import_skos.py
thesaurus/migrations/0001_initial.py
thesaurus/migrations/__init__.py